{
  "postId": "335748",
  "date": "2025-02-07T12:18:13.806Z",
  "content": "Climate change is hitting Russia hard, with winters getting warmer and summers seeing more droughts and wildfires. Scientists warn that 2025 will see a rise in extreme weather events. This could lead to Russia having no snow for 30 years, a drastic change for the country. Moscow is already feeling the effects, with unusual temperature fluctuations. The consequences of climate change are becoming more apparent, and it's essential to take action. Russia's future climate is looking uncertain, with potentially severe impacts on the environment and daily life.",
  "images": [],
  "generatedAt": "2025-02-07T12:18:13.806Z"
}